<?xml version="1.0" encoding="UTF-8"?>

<databaseChangeLog
        xmlns="http://www.liquibase.org/xml/ns/dbchangelog"
        xmlns:xsi="http://www.w3.org/2001/XMLSchema-instance"
        xsi:schemaLocation="http://www.liquibase.org/xml/ns/dbchangelog http://www.liquibase.org/xml/ns/dbchangelog/dbchangelog-3.6.xsd"
        logicalFilePath="sequences.xml">


    <changeSet id="seq_users" author="mikael">
        <createSequence incrementBy="1"
                        sequenceName="seq_users"
                        startValue="2"/>
    </changeSet>

    <changeSet id="seq_account" author="mikael">
        <createSequence incrementBy="1"
                        sequenceName="seq_account"
                        startValue="1"/>
    </changeSet>

    <changeSet id="seq_closedate" author="mikael">
        <createSequence incrementBy="1"
                        sequenceName="seq_closedate"
                        startValue="1"/>
    </changeSet>

    <changeSet id="seq_monthlycheck" author="mikael">
        <createSequence incrementBy="1"
                        sequenceName="seq_monthlycheck"
                        startValue="1"/>
    </changeSet>

    <changeSet id="seq_participation" author="mikael">
        <createSequence incrementBy="1"
                        sequenceName="seq_participation"
                        startValue="1"/>
    </changeSet>

    <changeSet id="seq_systemproperty" author="mikael">
        <createSequence incrementBy="1"
                        sequenceName="seq_systemproperty"
                        startValue="1"/>
    </changeSet>

    <changeSet id="seq_publicspecialDay" author="mikael">
        <createSequence incrementBy="1"
                        sequenceName="seq_publicspecialDay"
                        startValue="1"/>
    </changeSet>

    <changeSet id="seq_task" author="mikael">
        <createSequence incrementBy="1"
                        sequenceName="seq_task"
                        startValue="1"/>
    </changeSet>

    <changeSet id="seq_timeentry" author="mikael">
        <createSequence incrementBy="1"
                        sequenceName="seq_timeentry"
                        startValue="1"/>
    </changeSet>

</databaseChangeLog>